dj_annotatable_field/__init__.py
dj_annotatable_field/core.py
dj_annotatable_field-0.1.0.dist-info/WHEEL
dj_annotatable_field-0.1.0.dist-info/METADATA
dj_annotatable_field-0.1.0.dist-info/RECORD
