Metadata-Version: 2.1
Name: dj-annotatable-field
Version: 0.1.0
Summary: 
Author: massover
Author-email: joshm@simplebet.io
Requires-Python: >=3.7,<4.0
Classifier: Programming Language :: Python :: 3
Classifier: Programming Language :: Python :: 3.7
Classifier: Programming Language :: Python :: 3.8
Classifier: Programming Language :: Python :: 3.9
Requires-Dist: Django (>=3.2.6,<4.0.0)
